<annotation>
  <folder>VOC2007</folder>
  <filename>1479503265797441734.jpg</filename>
  <source>
    <database>The VOC2007 Database</database>
    <annotation>PASCAL VOC2007</annotation>
    <image>Udacity_object_dataset_2</image>
    <flickerid>0000000000</flickerid>
  </source>
  <owner>
    <flickerid>GO BLUE</flickerid>
    <name>UMD_ISL</name>
  </owner>
  <size>
    <width>1920</width>
    <height>1200</height>
    <depth>3</depth>
  </size>
  <segmentation>0</segmentation>
  <object>
    <name>truck</name>
    <pose>unspecified</pose>
    <truncated>0</truncated>
    <difficult>0</difficult>
    <bndbox>
      <xmin>1282</xmin>
      <ymin>440</ymin>
      <xmax>1536</xmax>
      <ymax>679</ymax>
    </bndbox>
  </object>
  <object>
    <name>car</name>
    <pose>unspecified</pose>
    <truncated>0</truncated>
    <difficult>0</difficult>
    <bndbox>
      <xmin>1703</xmin>
      <ymin>562</ymin>
      <xmax>1920</xmax>
      <ymax>802</ymax>
    </bndbox>
  </object>
  <object>
    <name>car</name>
    <pose>unspecified</pose>
    <truncated>0</truncated>
    <difficult>0</difficult>
    <bndbox>
      <xmin>1172</xmin>
      <ymin>556</ymin>
      <xmax>1268</xmax>
      <ymax>634</ymax>
    </bndbox>
  </object>
  <object>
    <name>car</name>
    <pose>unspecified</pose>
    <truncated>0</truncated>
    <difficult>0</difficult>
    <bndbox>
      <xmin>70</xmin>
      <ymin>593</ymin>
      <xmax>231</xmax>
      <ymax>679</ymax>
    </bndbox>
  </object>
  <object>
    <name>car</name>
    <pose>unspecified</pose>
    <truncated>0</truncated>
    <difficult>0</difficult>
    <bndbox>
      <xmin>1147</xmin>
      <ymin>568</ymin>
      <xmax>1192</xmax>
      <ymax>616</ymax>
    </bndbox>
  </object>
  <object>
    <name>pedestrian</name>
    <pose>unspecified</pose>
    <truncated>0</truncated>
    <difficult>0</difficult>
    <bndbox>
      <xmin>1593</xmin>
      <ymin>521</ymin>
      <xmax>1642</xmax>
      <ymax>656</ymax>
    </bndbox>
  </object>
  <object>
    <name>pedestrian</name>
    <pose>unspecified</pose>
    <truncated>0</truncated>
    <difficult>0</difficult>
    <bndbox>
      <xmin>1067</xmin>
      <ymin>562</ymin>
      <xmax>1100</xmax>
      <ymax>605</ymax>
    </bndbox>
  </object>
</annotation>
