<annotation>
  <folder>VOC2007</folder>
  <filename>1479502367235576953.jpg</filename>
  <source>
    <database>The VOC2007 Database</database>
    <annotation>PASCAL VOC2007</annotation>
    <image>Udacity_object_dataset_2</image>
    <flickerid>0000000000</flickerid>
  </source>
  <owner>
    <flickerid>GO BLUE</flickerid>
    <name>UMD_ISL</name>
  </owner>
  <size>
    <width>1920</width>
    <height>1200</height>
    <depth>3</depth>
  </size>
  <segmentation>0</segmentation>
  <object>
    <name>car</name>
    <pose>unspecified</pose>
    <truncated>0</truncated>
    <difficult>0</difficult>
    <bndbox>
      <xmin>1290</xmin>
      <ymin>511</ymin>
      <xmax>1784</xmax>
      <ymax>808</ymax>
    </bndbox>
  </object>
  <object>
    <name>car</name>
    <pose>unspecified</pose>
    <truncated>0</truncated>
    <difficult>0</difficult>
    <bndbox>
      <xmin>960</xmin>
      <ymin>572</ymin>
      <xmax>1096</xmax>
      <ymax>666</ymax>
    </bndbox>
  </object>
  <object>
    <name>car</name>
    <pose>unspecified</pose>
    <truncated>0</truncated>
    <difficult>0</difficult>
    <bndbox>
      <xmin>690</xmin>
      <ymin>543</ymin>
      <xmax>909</xmax>
      <ymax>719</ymax>
    </bndbox>
  </object>
  <object>
    <name>car</name>
    <pose>unspecified</pose>
    <truncated>0</truncated>
    <difficult>0</difficult>
    <bndbox>
      <xmin>582</xmin>
      <ymin>554</ymin>
      <xmax>686</xmax>
      <ymax>648</ymax>
    </bndbox>
  </object>
  <object>
    <name>car</name>
    <pose>unspecified</pose>
    <truncated>0</truncated>
    <difficult>0</difficult>
    <bndbox>
      <xmin>143</xmin>
      <ymin>539</ymin>
      <xmax>532</xmax>
      <ymax>757</ymax>
    </bndbox>
  </object>
  <object>
    <name>car</name>
    <pose>unspecified</pose>
    <truncated>0</truncated>
    <difficult>0</difficult>
    <bndbox>
      <xmin>98</xmin>
      <ymin>552</ymin>
      <xmax>192</xmax>
      <ymax>639</ymax>
    </bndbox>
  </object>
  <object>
    <name>car</name>
    <pose>unspecified</pose>
    <truncated>0</truncated>
    <difficult>0</difficult>
    <bndbox>
      <xmin>9</xmin>
      <ymin>543</ymin>
      <xmax>109</xmax>
      <ymax>646</ymax>
    </bndbox>
  </object>
</annotation>
