<annotation>
  <folder>VOC2007</folder>
  <filename>1479502419742451757.jpg</filename>
  <source>
    <database>The VOC2007 Database</database>
    <annotation>PASCAL VOC2007</annotation>
    <image>Udacity_object_dataset_2</image>
    <flickerid>0000000000</flickerid>
  </source>
  <owner>
    <flickerid>GO BLUE</flickerid>
    <name>UMD_ISL</name>
  </owner>
  <size>
    <width>1920</width>
    <height>1200</height>
    <depth>3</depth>
  </size>
  <segmentation>0</segmentation>
  <object>
    <name>car</name>
    <pose>unspecified</pose>
    <truncated>0</truncated>
    <difficult>0</difficult>
    <bndbox>
      <xmin>685</xmin>
      <ymin>538</ymin>
      <xmax>846</xmax>
      <ymax>667</ymax>
    </bndbox>
  </object>
  <object>
    <name>car</name>
    <pose>unspecified</pose>
    <truncated>0</truncated>
    <difficult>0</difficult>
    <bndbox>
      <xmin>1221</xmin>
      <ymin>524</ymin>
      <xmax>1529</xmax>
      <ymax>755</ymax>
    </bndbox>
  </object>
  <object>
    <name>car</name>
    <pose>unspecified</pose>
    <truncated>0</truncated>
    <difficult>0</difficult>
    <bndbox>
      <xmin>928</xmin>
      <ymin>552</ymin>
      <xmax>1014</xmax>
      <ymax>634</ymax>
    </bndbox>
  </object>
  <object>
    <name>car</name>
    <pose>unspecified</pose>
    <truncated>0</truncated>
    <difficult>0</difficult>
    <bndbox>
      <xmin>829</xmin>
      <ymin>572</ymin>
      <xmax>866</xmax>
      <ymax>620</ymax>
    </bndbox>
  </object>
  <object>
    <name>car</name>
    <pose>unspecified</pose>
    <truncated>0</truncated>
    <difficult>0</difficult>
    <bndbox>
      <xmin>1024</xmin>
      <ymin>570</ymin>
      <xmax>1067</xmax>
      <ymax>608</ymax>
    </bndbox>
  </object>
  <object>
    <name>truck</name>
    <pose>unspecified</pose>
    <truncated>0</truncated>
    <difficult>0</difficult>
    <bndbox>
      <xmin>10</xmin>
      <ymin>457</ymin>
      <xmax>248</xmax>
      <ymax>670</ymax>
    </bndbox>
  </object>
</annotation>
