<annotation>
  <folder>VOC2007</folder>
  <filename>1479504656890580491.jpg</filename>
  <source>
    <database>The VOC2007 Database</database>
    <annotation>PASCAL VOC2007</annotation>
    <image>Udacity_object_dataset_2</image>
    <flickerid>0000000000</flickerid>
  </source>
  <owner>
    <flickerid>GO BLUE</flickerid>
    <name>UMD_ISL</name>
  </owner>
  <size>
    <width>1920</width>
    <height>1200</height>
    <depth>3</depth>
  </size>
  <segmentation>0</segmentation>
  <object>
    <name>pedestrian</name>
    <pose>unspecified</pose>
    <truncated>0</truncated>
    <difficult>0</difficult>
    <bndbox>
      <xmin>1480</xmin>
      <ymin>458</ymin>
      <xmax>1589</xmax>
      <ymax>714</ymax>
    </bndbox>
  </object>
  <object>
    <name>car</name>
    <pose>unspecified</pose>
    <truncated>0</truncated>
    <difficult>0</difficult>
    <bndbox>
      <xmin>658</xmin>
      <ymin>407</ymin>
      <xmax>1105</xmax>
      <ymax>817</ymax>
    </bndbox>
  </object>
  <object>
    <name>truck</name>
    <pose>unspecified</pose>
    <truncated>0</truncated>
    <difficult>0</difficult>
    <bndbox>
      <xmin>1694</xmin>
      <ymin>405</ymin>
      <xmax>1911</xmax>
      <ymax>667</ymax>
    </bndbox>
  </object>
  <object>
    <name>pedestrian</name>
    <pose>unspecified</pose>
    <truncated>0</truncated>
    <difficult>0</difficult>
    <bndbox>
      <xmin>221</xmin>
      <ymin>529</ymin>
      <xmax>267</xmax>
      <ymax>641</ymax>
    </bndbox>
  </object>
  <object>
    <name>pedestrian</name>
    <pose>unspecified</pose>
    <truncated>0</truncated>
    <difficult>0</difficult>
    <bndbox>
      <xmin>270</xmin>
      <ymin>527</ymin>
      <xmax>321</xmax>
      <ymax>635</ymax>
    </bndbox>
  </object>
  <object>
    <name>pedestrian</name>
    <pose>unspecified</pose>
    <truncated>0</truncated>
    <difficult>0</difficult>
    <bndbox>
      <xmin>356</xmin>
      <ymin>527</ymin>
      <xmax>392</xmax>
      <ymax>640</ymax>
    </bndbox>
  </object>
  <object>
    <name>pedestrian</name>
    <pose>unspecified</pose>
    <truncated>0</truncated>
    <difficult>0</difficult>
    <bndbox>
      <xmin>389</xmin>
      <ymin>515</ymin>
      <xmax>419</xmax>
      <ymax>644</ymax>
    </bndbox>
  </object>
  <object>
    <name>pedestrian</name>
    <pose>unspecified</pose>
    <truncated>0</truncated>
    <difficult>0</difficult>
    <bndbox>
      <xmin>1126</xmin>
      <ymin>547</ymin>
      <xmax>1164</xmax>
      <ymax>613</ymax>
    </bndbox>
  </object>
  <object>
    <name>pedestrian</name>
    <pose>unspecified</pose>
    <truncated>0</truncated>
    <difficult>0</difficult>
    <bndbox>
      <xmin>1198</xmin>
      <ymin>536</ymin>
      <xmax>1230</xmax>
      <ymax>614</ymax>
    </bndbox>
  </object>
  <object>
    <name>pedestrian</name>
    <pose>unspecified</pose>
    <truncated>0</truncated>
    <difficult>0</difficult>
    <bndbox>
      <xmin>1237</xmin>
      <ymin>527</ymin>
      <xmax>1267</xmax>
      <ymax>622</ymax>
    </bndbox>
  </object>
  <object>
    <name>pedestrian</name>
    <pose>unspecified</pose>
    <truncated>0</truncated>
    <difficult>0</difficult>
    <bndbox>
      <xmin>1455</xmin>
      <ymin>500</ymin>
      <xmax>1485</xmax>
      <ymax>632</ymax>
    </bndbox>
  </object>
  <object>
    <name>pedestrian</name>
    <pose>unspecified</pose>
    <truncated>0</truncated>
    <difficult>0</difficult>
    <bndbox>
      <xmin>1794</xmin>
      <ymin>461</ymin>
      <xmax>1902</xmax>
      <ymax>707</ymax>
    </bndbox>
  </object>
  <object>
    <name>car</name>
    <pose>unspecified</pose>
    <truncated>0</truncated>
    <difficult>0</difficult>
    <bndbox>
      <xmin>635</xmin>
      <ymin>556</ymin>
      <xmax>678</xmax>
      <ymax>614</ymax>
    </bndbox>
  </object>
</annotation>
