<annotation>
  <folder>VOC2007</folder>
  <filename>1479499344529905538.jpg</filename>
  <source>
    <database>The VOC2007 Database</database>
    <annotation>PASCAL VOC2007</annotation>
    <image>Udacity_object_dataset_2</image>
    <flickerid>0000000000</flickerid>
  </source>
  <owner>
    <flickerid>GO BLUE</flickerid>
    <name>UMD_ISL</name>
  </owner>
  <size>
    <width>1920</width>
    <height>1200</height>
    <depth>3</depth>
  </size>
  <segmentation>0</segmentation>
  <object>
    <name>car</name>
    <pose>unspecified</pose>
    <truncated>0</truncated>
    <difficult>0</difficult>
    <bndbox>
      <xmin>683</xmin>
      <ymin>524</ymin>
      <xmax>886</xmax>
      <ymax>703</ymax>
    </bndbox>
  </object>
  <object>
    <name>car</name>
    <pose>unspecified</pose>
    <truncated>0</truncated>
    <difficult>0</difficult>
    <bndbox>
      <xmin>8</xmin>
      <ymin>573</ymin>
      <xmax>147</xmax>
      <ymax>683</ymax>
    </bndbox>
  </object>
  <object>
    <name>car</name>
    <pose>unspecified</pose>
    <truncated>0</truncated>
    <difficult>0</difficult>
    <bndbox>
      <xmin>176</xmin>
      <ymin>573</ymin>
      <xmax>327</xmax>
      <ymax>665</ymax>
    </bndbox>
  </object>
  <object>
    <name>car</name>
    <pose>unspecified</pose>
    <truncated>0</truncated>
    <difficult>0</difficult>
    <bndbox>
      <xmin>365</xmin>
      <ymin>575</ymin>
      <xmax>486</xmax>
      <ymax>654</ymax>
    </bndbox>
  </object>
  <object>
    <name>car</name>
    <pose>unspecified</pose>
    <truncated>0</truncated>
    <difficult>0</difficult>
    <bndbox>
      <xmin>483</xmin>
      <ymin>589</ymin>
      <xmax>560</xmax>
      <ymax>640</ymax>
    </bndbox>
  </object>
  <object>
    <name>car</name>
    <pose>unspecified</pose>
    <truncated>0</truncated>
    <difficult>0</difficult>
    <bndbox>
      <xmin>534</xmin>
      <ymin>573</ymin>
      <xmax>618</xmax>
      <ymax>641</ymax>
    </bndbox>
  </object>
  <object>
    <name>car</name>
    <pose>unspecified</pose>
    <truncated>0</truncated>
    <difficult>0</difficult>
    <bndbox>
      <xmin>616</xmin>
      <ymin>585</ymin>
      <xmax>677</xmax>
      <ymax>640</ymax>
    </bndbox>
  </object>
  <object>
    <name>car</name>
    <pose>unspecified</pose>
    <truncated>0</truncated>
    <difficult>0</difficult>
    <bndbox>
      <xmin>671</xmin>
      <ymin>586</ymin>
      <xmax>705</xmax>
      <ymax>629</ymax>
    </bndbox>
  </object>
  <object>
    <name>car</name>
    <pose>unspecified</pose>
    <truncated>0</truncated>
    <difficult>0</difficult>
    <bndbox>
      <xmin>123</xmin>
      <ymin>568</ymin>
      <xmax>209</xmax>
      <ymax>654</ymax>
    </bndbox>
  </object>
  <object>
    <name>car</name>
    <pose>unspecified</pose>
    <truncated>0</truncated>
    <difficult>0</difficult>
    <bndbox>
      <xmin>926</xmin>
      <ymin>595</ymin>
      <xmax>951</xmax>
      <ymax>616</ymax>
    </bndbox>
  </object>
  <object>
    <name>car</name>
    <pose>unspecified</pose>
    <truncated>0</truncated>
    <difficult>0</difficult>
    <bndbox>
      <xmin>965</xmin>
      <ymin>591</ymin>
      <xmax>990</xmax>
      <ymax>614</ymax>
    </bndbox>
  </object>
  <object>
    <name>truck</name>
    <pose>unspecified</pose>
    <truncated>0</truncated>
    <difficult>0</difficult>
    <bndbox>
      <xmin>554</xmin>
      <ymin>554</ymin>
      <xmax>639</xmax>
      <ymax>593</ymax>
    </bndbox>
  </object>
</annotation>
