<annotation>
  <folder>VOC2007</folder>
  <filename>1479505306933148553.jpg</filename>
  <source>
    <database>The VOC2007 Database</database>
    <annotation>PASCAL VOC2007</annotation>
    <image>Udacity_object_dataset_2</image>
    <flickerid>0000000000</flickerid>
  </source>
  <owner>
    <flickerid>GO BLUE</flickerid>
    <name>UMD_ISL</name>
  </owner>
  <size>
    <width>1920</width>
    <height>1200</height>
    <depth>3</depth>
  </size>
  <segmentation>0</segmentation>
  <object>
    <name>car</name>
    <pose>unspecified</pose>
    <truncated>0</truncated>
    <difficult>0</difficult>
    <bndbox>
      <xmin>1372</xmin>
      <ymin>535</ymin>
      <xmax>1920</xmax>
      <ymax>943</ymax>
    </bndbox>
  </object>
  <object>
    <name>car</name>
    <pose>unspecified</pose>
    <truncated>0</truncated>
    <difficult>0</difficult>
    <bndbox>
      <xmin>1144</xmin>
      <ymin>583</ymin>
      <xmax>1279</xmax>
      <ymax>694</ymax>
    </bndbox>
  </object>
  <object>
    <name>car</name>
    <pose>unspecified</pose>
    <truncated>0</truncated>
    <difficult>0</difficult>
    <bndbox>
      <xmin>1120</xmin>
      <ymin>586</ymin>
      <xmax>1182</xmax>
      <ymax>653</ymax>
    </bndbox>
  </object>
  <object>
    <name>car</name>
    <pose>unspecified</pose>
    <truncated>0</truncated>
    <difficult>0</difficult>
    <bndbox>
      <xmin>702</xmin>
      <ymin>588</ymin>
      <xmax>827</xmax>
      <ymax>681</ymax>
    </bndbox>
  </object>
  <object>
    <name>car</name>
    <pose>unspecified</pose>
    <truncated>0</truncated>
    <difficult>0</difficult>
    <bndbox>
      <xmin>858</xmin>
      <ymin>584</ymin>
      <xmax>915</xmax>
      <ymax>651</ymax>
    </bndbox>
  </object>
  <object>
    <name>car</name>
    <pose>unspecified</pose>
    <truncated>0</truncated>
    <difficult>0</difficult>
    <bndbox>
      <xmin>943</xmin>
      <ymin>588</ymin>
      <xmax>981</xmax>
      <ymax>626</ymax>
    </bndbox>
  </object>
  <object>
    <name>car</name>
    <pose>unspecified</pose>
    <truncated>0</truncated>
    <difficult>0</difficult>
    <bndbox>
      <xmin>815</xmin>
      <ymin>593</ymin>
      <xmax>860</xmax>
      <ymax>670</ymax>
    </bndbox>
  </object>
  <object>
    <name>car</name>
    <pose>unspecified</pose>
    <truncated>0</truncated>
    <difficult>0</difficult>
    <bndbox>
      <xmin>901</xmin>
      <ymin>598</ymin>
      <xmax>939</xmax>
      <ymax>646</ymax>
    </bndbox>
  </object>
  <object>
    <name>car</name>
    <pose>unspecified</pose>
    <truncated>0</truncated>
    <difficult>0</difficult>
    <bndbox>
      <xmin>1108</xmin>
      <ymin>587</ymin>
      <xmax>1149</xmax>
      <ymax>646</ymax>
    </bndbox>
  </object>
</annotation>
