<annotation>
  <folder>VOC2007</folder>
  <filename>1479504401372898846.jpg</filename>
  <source>
    <database>The VOC2007 Database</database>
    <annotation>PASCAL VOC2007</annotation>
    <image>Udacity_object_dataset_2</image>
    <flickerid>0000000000</flickerid>
  </source>
  <owner>
    <flickerid>GO BLUE</flickerid>
    <name>UMD_ISL</name>
  </owner>
  <size>
    <width>1920</width>
    <height>1200</height>
    <depth>3</depth>
  </size>
  <segmentation>0</segmentation>
  <object>
    <name>car</name>
    <pose>unspecified</pose>
    <truncated>0</truncated>
    <difficult>0</difficult>
    <bndbox>
      <xmin>1639</xmin>
      <ymin>550</ymin>
      <xmax>1919</xmax>
      <ymax>738</ymax>
    </bndbox>
  </object>
  <object>
    <name>car</name>
    <pose>unspecified</pose>
    <truncated>0</truncated>
    <difficult>0</difficult>
    <bndbox>
      <xmin>1452</xmin>
      <ymin>546</ymin>
      <xmax>1711</xmax>
      <ymax>690</ymax>
    </bndbox>
  </object>
  <object>
    <name>car</name>
    <pose>unspecified</pose>
    <truncated>0</truncated>
    <difficult>0</difficult>
    <bndbox>
      <xmin>1379</xmin>
      <ymin>540</ymin>
      <xmax>1530</xmax>
      <ymax>663</ymax>
    </bndbox>
  </object>
  <object>
    <name>car</name>
    <pose>unspecified</pose>
    <truncated>0</truncated>
    <difficult>0</difficult>
    <bndbox>
      <xmin>1276</xmin>
      <ymin>555</ymin>
      <xmax>1411</xmax>
      <ymax>640</ymax>
    </bndbox>
  </object>
  <object>
    <name>car</name>
    <pose>unspecified</pose>
    <truncated>0</truncated>
    <difficult>0</difficult>
    <bndbox>
      <xmin>1230</xmin>
      <ymin>557</ymin>
      <xmax>1313</xmax>
      <ymax>630</ymax>
    </bndbox>
  </object>
  <object>
    <name>car</name>
    <pose>unspecified</pose>
    <truncated>0</truncated>
    <difficult>0</difficult>
    <bndbox>
      <xmin>938</xmin>
      <ymin>566</ymin>
      <xmax>966</xmax>
      <ymax>594</ymax>
    </bndbox>
  </object>
  <object>
    <name>truck</name>
    <pose>unspecified</pose>
    <truncated>0</truncated>
    <difficult>0</difficult>
    <bndbox>
      <xmin>1018</xmin>
      <ymin>551</ymin>
      <xmax>1092</xmax>
      <ymax>581</ymax>
    </bndbox>
  </object>
  <object>
    <name>car</name>
    <pose>unspecified</pose>
    <truncated>0</truncated>
    <difficult>0</difficult>
    <bndbox>
      <xmin>1080</xmin>
      <ymin>565</ymin>
      <xmax>1121</xmax>
      <ymax>593</ymax>
    </bndbox>
  </object>
  <object>
    <name>car</name>
    <pose>unspecified</pose>
    <truncated>0</truncated>
    <difficult>0</difficult>
    <bndbox>
      <xmin>33</xmin>
      <ymin>536</ymin>
      <xmax>298</xmax>
      <ymax>681</ymax>
    </bndbox>
  </object>
  <object>
    <name>truck</name>
    <pose>unspecified</pose>
    <truncated>0</truncated>
    <difficult>0</difficult>
    <bndbox>
      <xmin>505</xmin>
      <ymin>535</ymin>
      <xmax>657</xmax>
      <ymax>631</ymax>
    </bndbox>
  </object>
  <object>
    <name>truck</name>
    <pose>unspecified</pose>
    <truncated>0</truncated>
    <difficult>0</difficult>
    <bndbox>
      <xmin>697</xmin>
      <ymin>540</ymin>
      <xmax>760</xmax>
      <ymax>612</ymax>
    </bndbox>
  </object>
  <object>
    <name>car</name>
    <pose>unspecified</pose>
    <truncated>0</truncated>
    <difficult>0</difficult>
    <bndbox>
      <xmin>1742</xmin>
      <ymin>501</ymin>
      <xmax>1864</xmax>
      <ymax>563</ymax>
    </bndbox>
  </object>
  <object>
    <name>car</name>
    <pose>unspecified</pose>
    <truncated>0</truncated>
    <difficult>0</difficult>
    <bndbox>
      <xmin>1195</xmin>
      <ymin>537</ymin>
      <xmax>1308</xmax>
      <ymax>623</ymax>
    </bndbox>
  </object>
</annotation>
