<annotation>
  <folder>VOC2007</folder>
  <filename>1479505928477126511.jpg</filename>
  <source>
    <database>The VOC2007 Database</database>
    <annotation>PASCAL VOC2007</annotation>
    <image>Udacity_object_dataset_2</image>
    <flickerid>0000000000</flickerid>
  </source>
  <owner>
    <flickerid>GO BLUE</flickerid>
    <name>UMD_ISL</name>
  </owner>
  <size>
    <width>1920</width>
    <height>1200</height>
    <depth>3</depth>
  </size>
  <segmentation>0</segmentation>
  <object>
    <name>car</name>
    <pose>unspecified</pose>
    <truncated>0</truncated>
    <difficult>0</difficult>
    <bndbox>
      <xmin>4</xmin>
      <ymin>505</ymin>
      <xmax>268</xmax>
      <ymax>745</ymax>
    </bndbox>
  </object>
  <object>
    <name>car</name>
    <pose>unspecified</pose>
    <truncated>0</truncated>
    <difficult>0</difficult>
    <bndbox>
      <xmin>650</xmin>
      <ymin>520</ymin>
      <xmax>791</xmax>
      <ymax>664</ymax>
    </bndbox>
  </object>
  <object>
    <name>car</name>
    <pose>unspecified</pose>
    <truncated>0</truncated>
    <difficult>0</difficult>
    <bndbox>
      <xmin>1080</xmin>
      <ymin>551</ymin>
      <xmax>1193</xmax>
      <ymax>634</ymax>
    </bndbox>
  </object>
  <object>
    <name>car</name>
    <pose>unspecified</pose>
    <truncated>0</truncated>
    <difficult>0</difficult>
    <bndbox>
      <xmin>1359</xmin>
      <ymin>433</ymin>
      <xmax>1920</xmax>
      <ymax>863</ymax>
    </bndbox>
  </object>
  <object>
    <name>car</name>
    <pose>unspecified</pose>
    <truncated>0</truncated>
    <difficult>0</difficult>
    <bndbox>
      <xmin>797</xmin>
      <ymin>561</ymin>
      <xmax>835</xmax>
      <ymax>627</ymax>
    </bndbox>
  </object>
  <object>
    <name>car</name>
    <pose>unspecified</pose>
    <truncated>0</truncated>
    <difficult>0</difficult>
    <bndbox>
      <xmin>818</xmin>
      <ymin>568</ymin>
      <xmax>852</xmax>
      <ymax>618</ymax>
    </bndbox>
  </object>
  <object>
    <name>truck</name>
    <pose>unspecified</pose>
    <truncated>0</truncated>
    <difficult>0</difficult>
    <bndbox>
      <xmin>883</xmin>
      <ymin>505</ymin>
      <xmax>982</xmax>
      <ymax>613</ymax>
    </bndbox>
  </object>
  <object>
    <name>car</name>
    <pose>unspecified</pose>
    <truncated>0</truncated>
    <difficult>0</difficult>
    <bndbox>
      <xmin>915</xmin>
      <ymin>562</ymin>
      <xmax>971</xmax>
      <ymax>615</ymax>
    </bndbox>
  </object>
</annotation>
