<annotation>
  <folder>VOC2007</folder>
  <filename>1478901030797341212.jpg</filename>
  <source>
    <database>The VOC2007 Database</database>
    <annotation>PASCAL VOC2007</annotation>
    <image>Udacity_object_dataset_2</image>
    <flickerid>0000000000</flickerid>
  </source>
  <owner>
    <flickerid>GO BLUE</flickerid>
    <name>UMD_ISL</name>
  </owner>
  <size>
    <width>1920</width>
    <height>1200</height>
    <depth>3</depth>
  </size>
  <segmentation>0</segmentation>
  <object>
    <name>car</name>
    <pose>unspecified</pose>
    <truncated>0</truncated>
    <difficult>0</difficult>
    <bndbox>
      <xmin>578</xmin>
      <ymin>590</ymin>
      <xmax>688</xmax>
      <ymax>678</ymax>
    </bndbox>
  </object>
  <object>
    <name>car</name>
    <pose>unspecified</pose>
    <truncated>0</truncated>
    <difficult>0</difficult>
    <bndbox>
      <xmin>690</xmin>
      <ymin>592</ymin>
      <xmax>748</xmax>
      <ymax>660</ymax>
    </bndbox>
  </object>
  <object>
    <name>car</name>
    <pose>unspecified</pose>
    <truncated>0</truncated>
    <difficult>0</difficult>
    <bndbox>
      <xmin>796</xmin>
      <ymin>604</ymin>
      <xmax>844</xmax>
      <ymax>640</ymax>
    </bndbox>
  </object>
  <object>
    <name>truck</name>
    <pose>unspecified</pose>
    <truncated>0</truncated>
    <difficult>0</difficult>
    <bndbox>
      <xmin>818</xmin>
      <ymin>568</ymin>
      <xmax>878</xmax>
      <ymax>642</ymax>
    </bndbox>
  </object>
  <object>
    <name>car</name>
    <pose>unspecified</pose>
    <truncated>0</truncated>
    <difficult>0</difficult>
    <bndbox>
      <xmin>824</xmin>
      <ymin>576</ymin>
      <xmax>872</xmax>
      <ymax>624</ymax>
    </bndbox>
  </object>
</annotation>
