<annotation>
  <folder>VOC2007</folder>
  <filename>1478899744252500910.jpg</filename>
  <source>
    <database>The VOC2007 Database</database>
    <annotation>PASCAL VOC2007</annotation>
    <image>Udacity_object_dataset_2</image>
    <flickerid>0000000000</flickerid>
  </source>
  <owner>
    <flickerid>GO BLUE</flickerid>
    <name>UMD_ISL</name>
  </owner>
  <size>
    <width>1920</width>
    <height>1200</height>
    <depth>3</depth>
  </size>
  <segmentation>0</segmentation>
  <object>
    <name>car</name>
    <pose>unspecified</pose>
    <truncated>0</truncated>
    <difficult>0</difficult>
    <bndbox>
      <xmin>6</xmin>
      <ymin>622</ymin>
      <xmax>270</xmax>
      <ymax>848</ymax>
    </bndbox>
  </object>
  <object>
    <name>car</name>
    <pose>unspecified</pose>
    <truncated>0</truncated>
    <difficult>0</difficult>
    <bndbox>
      <xmin>220</xmin>
      <ymin>618</ymin>
      <xmax>416</xmax>
      <ymax>774</ymax>
    </bndbox>
  </object>
  <object>
    <name>car</name>
    <pose>unspecified</pose>
    <truncated>0</truncated>
    <difficult>0</difficult>
    <bndbox>
      <xmin>376</xmin>
      <ymin>620</ymin>
      <xmax>496</xmax>
      <ymax>730</ymax>
    </bndbox>
  </object>
  <object>
    <name>car</name>
    <pose>unspecified</pose>
    <truncated>0</truncated>
    <difficult>0</difficult>
    <bndbox>
      <xmin>446</xmin>
      <ymin>596</ymin>
      <xmax>562</xmax>
      <ymax>724</ymax>
    </bndbox>
  </object>
  <object>
    <name>car</name>
    <pose>unspecified</pose>
    <truncated>0</truncated>
    <difficult>0</difficult>
    <bndbox>
      <xmin>478</xmin>
      <ymin>594</ymin>
      <xmax>568</xmax>
      <ymax>722</ymax>
    </bndbox>
  </object>
  <object>
    <name>car</name>
    <pose>unspecified</pose>
    <truncated>0</truncated>
    <difficult>0</difficult>
    <bndbox>
      <xmin>580</xmin>
      <ymin>614</ymin>
      <xmax>658</xmax>
      <ymax>668</ymax>
    </bndbox>
  </object>
  <object>
    <name>car</name>
    <pose>unspecified</pose>
    <truncated>0</truncated>
    <difficult>0</difficult>
    <bndbox>
      <xmin>678</xmin>
      <ymin>598</ymin>
      <xmax>760</xmax>
      <ymax>672</ymax>
    </bndbox>
  </object>
  <object>
    <name>car</name>
    <pose>unspecified</pose>
    <truncated>0</truncated>
    <difficult>0</difficult>
    <bndbox>
      <xmin>680</xmin>
      <ymin>602</ymin>
      <xmax>764</xmax>
      <ymax>662</ymax>
    </bndbox>
  </object>
  <object>
    <name>car</name>
    <pose>unspecified</pose>
    <truncated>0</truncated>
    <difficult>0</difficult>
    <bndbox>
      <xmin>948</xmin>
      <ymin>564</ymin>
      <xmax>1162</xmax>
      <ymax>732</ymax>
    </bndbox>
  </object>
  <object>
    <name>car</name>
    <pose>unspecified</pose>
    <truncated>0</truncated>
    <difficult>0</difficult>
    <bndbox>
      <xmin>1132</xmin>
      <ymin>566</ymin>
      <xmax>1916</xmax>
      <ymax>1046</ymax>
    </bndbox>
  </object>
  <object>
    <name>pedestrian</name>
    <pose>unspecified</pose>
    <truncated>0</truncated>
    <difficult>0</difficult>
    <bndbox>
      <xmin>1256</xmin>
      <ymin>552</ymin>
      <xmax>1314</xmax>
      <ymax>646</ymax>
    </bndbox>
  </object>
</annotation>
