<annotation>
  <folder>VOC2007</folder>
  <filename>1478898321169765754.jpg</filename>
  <source>
    <database>The VOC2007 Database</database>
    <annotation>PASCAL VOC2007</annotation>
    <image>Udacity_object_dataset_2</image>
    <flickerid>0000000000</flickerid>
  </source>
  <owner>
    <flickerid>GO BLUE</flickerid>
    <name>UMD_ISL</name>
  </owner>
  <size>
    <width>1920</width>
    <height>1200</height>
    <depth>3</depth>
  </size>
  <segmentation>0</segmentation>
  <object>
    <name>car</name>
    <pose>unspecified</pose>
    <truncated>0</truncated>
    <difficult>0</difficult>
    <bndbox>
      <xmin>322</xmin>
      <ymin>536</ymin>
      <xmax>946</xmax>
      <ymax>1028</ymax>
    </bndbox>
  </object>
  <object>
    <name>trafficLight</name>
    <pose>unspecified</pose>
    <truncated>0</truncated>
    <difficult>0</difficult>
    <bndbox>
      <xmin>520</xmin>
      <ymin>296</ymin>
      <xmax>558</xmax>
      <ymax>366</ymax>
    </bndbox>
  </object>
  <object>
    <name>trafficLight</name>
    <pose>unspecified</pose>
    <truncated>0</truncated>
    <difficult>0</difficult>
    <bndbox>
      <xmin>734</xmin>
      <ymin>304</ymin>
      <xmax>766</xmax>
      <ymax>384</ymax>
    </bndbox>
  </object>
  <object>
    <name>pedestrian</name>
    <pose>unspecified</pose>
    <truncated>0</truncated>
    <difficult>0</difficult>
    <bndbox>
      <xmin>1016</xmin>
      <ymin>586</ymin>
      <xmax>1044</xmax>
      <ymax>682</ymax>
    </bndbox>
  </object>
  <object>
    <name>pedestrian</name>
    <pose>unspecified</pose>
    <truncated>0</truncated>
    <difficult>0</difficult>
    <bndbox>
      <xmin>1036</xmin>
      <ymin>580</ymin>
      <xmax>1062</xmax>
      <ymax>666</ymax>
    </bndbox>
  </object>
  <object>
    <name>trafficLight</name>
    <pose>unspecified</pose>
    <truncated>0</truncated>
    <difficult>0</difficult>
    <bndbox>
      <xmin>1062</xmin>
      <ymin>452</ymin>
      <xmax>1098</xmax>
      <ymax>526</ymax>
    </bndbox>
  </object>
  <object>
    <name>pedestrian</name>
    <pose>unspecified</pose>
    <truncated>0</truncated>
    <difficult>0</difficult>
    <bndbox>
      <xmin>1070</xmin>
      <ymin>572</ymin>
      <xmax>1114</xmax>
      <ymax>686</ymax>
    </bndbox>
  </object>
  <object>
    <name>pedestrian</name>
    <pose>unspecified</pose>
    <truncated>0</truncated>
    <difficult>0</difficult>
    <bndbox>
      <xmin>1098</xmin>
      <ymin>576</ymin>
      <xmax>1138</xmax>
      <ymax>664</ymax>
    </bndbox>
  </object>
  <object>
    <name>pedestrian</name>
    <pose>unspecified</pose>
    <truncated>0</truncated>
    <difficult>0</difficult>
    <bndbox>
      <xmin>1100</xmin>
      <ymin>572</ymin>
      <xmax>1142</xmax>
      <ymax>670</ymax>
    </bndbox>
  </object>
  <object>
    <name>biker</name>
    <pose>unspecified</pose>
    <truncated>0</truncated>
    <difficult>0</difficult>
    <bndbox>
      <xmin>1232</xmin>
      <ymin>578</ymin>
      <xmax>1304</xmax>
      <ymax>688</ymax>
    </bndbox>
  </object>
  <object>
    <name>biker</name>
    <pose>unspecified</pose>
    <truncated>0</truncated>
    <difficult>0</difficult>
    <bndbox>
      <xmin>1354</xmin>
      <ymin>572</ymin>
      <xmax>1476</xmax>
      <ymax>692</ymax>
    </bndbox>
  </object>
  <object>
    <name>car</name>
    <pose>unspecified</pose>
    <truncated>0</truncated>
    <difficult>0</difficult>
    <bndbox>
      <xmin>1738</xmin>
      <ymin>570</ymin>
      <xmax>1918</xmax>
      <ymax>674</ymax>
    </bndbox>
  </object>
</annotation>
