<annotation>
  <folder>VOC2007</folder>
  <filename>1478899211240082547.jpg</filename>
  <source>
    <database>The VOC2007 Database</database>
    <annotation>PASCAL VOC2007</annotation>
    <image>Udacity_object_dataset_2</image>
    <flickerid>0000000000</flickerid>
  </source>
  <owner>
    <flickerid>GO BLUE</flickerid>
    <name>UMD_ISL</name>
  </owner>
  <size>
    <width>1920</width>
    <height>1200</height>
    <depth>3</depth>
  </size>
  <segmentation>0</segmentation>
  <object>
    <name>car</name>
    <pose>unspecified</pose>
    <truncated>0</truncated>
    <difficult>0</difficult>
    <bndbox>
      <xmin>160</xmin>
      <ymin>616</ymin>
      <xmax>308</xmax>
      <ymax>704</ymax>
    </bndbox>
  </object>
  <object>
    <name>car</name>
    <pose>unspecified</pose>
    <truncated>0</truncated>
    <difficult>0</difficult>
    <bndbox>
      <xmin>282</xmin>
      <ymin>604</ymin>
      <xmax>382</xmax>
      <ymax>680</ymax>
    </bndbox>
  </object>
  <object>
    <name>car</name>
    <pose>unspecified</pose>
    <truncated>0</truncated>
    <difficult>0</difficult>
    <bndbox>
      <xmin>440</xmin>
      <ymin>600</ymin>
      <xmax>508</xmax>
      <ymax>658</ymax>
    </bndbox>
  </object>
  <object>
    <name>car</name>
    <pose>unspecified</pose>
    <truncated>0</truncated>
    <difficult>0</difficult>
    <bndbox>
      <xmin>722</xmin>
      <ymin>590</ymin>
      <xmax>804</xmax>
      <ymax>666</ymax>
    </bndbox>
  </object>
  <object>
    <name>car</name>
    <pose>unspecified</pose>
    <truncated>0</truncated>
    <difficult>0</difficult>
    <bndbox>
      <xmin>852</xmin>
      <ymin>600</ymin>
      <xmax>918</xmax>
      <ymax>648</ymax>
    </bndbox>
  </object>
  <object>
    <name>car</name>
    <pose>unspecified</pose>
    <truncated>0</truncated>
    <difficult>0</difficult>
    <bndbox>
      <xmin>896</xmin>
      <ymin>588</ymin>
      <xmax>940</xmax>
      <ymax>622</ymax>
    </bndbox>
  </object>
  <object>
    <name>car</name>
    <pose>unspecified</pose>
    <truncated>0</truncated>
    <difficult>0</difficult>
    <bndbox>
      <xmin>912</xmin>
      <ymin>580</ymin>
      <xmax>1032</xmax>
      <ymax>680</ymax>
    </bndbox>
  </object>
  <object>
    <name>car</name>
    <pose>unspecified</pose>
    <truncated>0</truncated>
    <difficult>0</difficult>
    <bndbox>
      <xmin>1128</xmin>
      <ymin>582</ymin>
      <xmax>1216</xmax>
      <ymax>656</ymax>
    </bndbox>
  </object>
  <object>
    <name>car</name>
    <pose>unspecified</pose>
    <truncated>0</truncated>
    <difficult>0</difficult>
    <bndbox>
      <xmin>1138</xmin>
      <ymin>588</ymin>
      <xmax>1230</xmax>
      <ymax>660</ymax>
    </bndbox>
  </object>
  <object>
    <name>car</name>
    <pose>unspecified</pose>
    <truncated>0</truncated>
    <difficult>0</difficult>
    <bndbox>
      <xmin>1250</xmin>
      <ymin>596</ymin>
      <xmax>1302</xmax>
      <ymax>676</ymax>
    </bndbox>
  </object>
  <object>
    <name>car</name>
    <pose>unspecified</pose>
    <truncated>0</truncated>
    <difficult>0</difficult>
    <bndbox>
      <xmin>1286</xmin>
      <ymin>572</ymin>
      <xmax>1416</xmax>
      <ymax>686</ymax>
    </bndbox>
  </object>
  <object>
    <name>car</name>
    <pose>unspecified</pose>
    <truncated>0</truncated>
    <difficult>0</difficult>
    <bndbox>
      <xmin>1378</xmin>
      <ymin>598</ymin>
      <xmax>1544</xmax>
      <ymax>686</ymax>
    </bndbox>
  </object>
</annotation>
