<annotation>
  <folder>VOC2007</folder>
  <filename>1478901424415630818.jpg</filename>
  <source>
    <database>The VOC2007 Database</database>
    <annotation>PASCAL VOC2007</annotation>
    <image>Udacity_object_dataset_2</image>
    <flickerid>0000000000</flickerid>
  </source>
  <owner>
    <flickerid>GO BLUE</flickerid>
    <name>UMD_ISL</name>
  </owner>
  <size>
    <width>1920</width>
    <height>1200</height>
    <depth>3</depth>
  </size>
  <segmentation>0</segmentation>
  <object>
    <name>car</name>
    <pose>unspecified</pose>
    <truncated>0</truncated>
    <difficult>0</difficult>
    <bndbox>
      <xmin>0</xmin>
      <ymin>618</ymin>
      <xmax>46</xmax>
      <ymax>672</ymax>
    </bndbox>
  </object>
  <object>
    <name>car</name>
    <pose>unspecified</pose>
    <truncated>0</truncated>
    <difficult>0</difficult>
    <bndbox>
      <xmin>182</xmin>
      <ymin>616</ymin>
      <xmax>318</xmax>
      <ymax>708</ymax>
    </bndbox>
  </object>
  <object>
    <name>car</name>
    <pose>unspecified</pose>
    <truncated>0</truncated>
    <difficult>0</difficult>
    <bndbox>
      <xmin>184</xmin>
      <ymin>606</ymin>
      <xmax>322</xmax>
      <ymax>708</ymax>
    </bndbox>
  </object>
  <object>
    <name>car</name>
    <pose>unspecified</pose>
    <truncated>0</truncated>
    <difficult>0</difficult>
    <bndbox>
      <xmin>380</xmin>
      <ymin>588</ymin>
      <xmax>592</xmax>
      <ymax>726</ymax>
    </bndbox>
  </object>
  <object>
    <name>car</name>
    <pose>unspecified</pose>
    <truncated>0</truncated>
    <difficult>0</difficult>
    <bndbox>
      <xmin>808</xmin>
      <ymin>580</ymin>
      <xmax>1080</xmax>
      <ymax>700</ymax>
    </bndbox>
  </object>
  <object>
    <name>car</name>
    <pose>unspecified</pose>
    <truncated>0</truncated>
    <difficult>0</difficult>
    <bndbox>
      <xmin>1252</xmin>
      <ymin>590</ymin>
      <xmax>1412</xmax>
      <ymax>668</ymax>
    </bndbox>
  </object>
  <object>
    <name>biker</name>
    <pose>unspecified</pose>
    <truncated>0</truncated>
    <difficult>0</difficult>
    <bndbox>
      <xmin>1590</xmin>
      <ymin>586</ymin>
      <xmax>1634</xmax>
      <ymax>632</ymax>
    </bndbox>
  </object>
</annotation>
