<annotation>
  <folder>VOC2007</folder>
  <filename>1478897158594635245.jpg</filename>
  <source>
    <database>The VOC2007 Database</database>
    <annotation>PASCAL VOC2007</annotation>
    <image>Udacity_object_dataset_2</image>
    <flickerid>0000000000</flickerid>
  </source>
  <owner>
    <flickerid>GO BLUE</flickerid>
    <name>UMD_ISL</name>
  </owner>
  <size>
    <width>1920</width>
    <height>1200</height>
    <depth>3</depth>
  </size>
  <segmentation>0</segmentation>
  <object>
    <name>truck</name>
    <pose>unspecified</pose>
    <truncated>0</truncated>
    <difficult>0</difficult>
    <bndbox>
      <xmin>0</xmin>
      <ymin>612</ymin>
      <xmax>252</xmax>
      <ymax>716</ymax>
    </bndbox>
  </object>
  <object>
    <name>car</name>
    <pose>unspecified</pose>
    <truncated>0</truncated>
    <difficult>0</difficult>
    <bndbox>
      <xmin>0</xmin>
      <ymin>616</ymin>
      <xmax>254</xmax>
      <ymax>722</ymax>
    </bndbox>
  </object>
  <object>
    <name>pedestrian</name>
    <pose>unspecified</pose>
    <truncated>0</truncated>
    <difficult>0</difficult>
    <bndbox>
      <xmin>74</xmin>
      <ymin>648</ymin>
      <xmax>120</xmax>
      <ymax>734</ymax>
    </bndbox>
  </object>
  <object>
    <name>truck</name>
    <pose>unspecified</pose>
    <truncated>0</truncated>
    <difficult>0</difficult>
    <bndbox>
      <xmin>198</xmin>
      <ymin>606</ymin>
      <xmax>334</xmax>
      <ymax>706</ymax>
    </bndbox>
  </object>
  <object>
    <name>car</name>
    <pose>unspecified</pose>
    <truncated>0</truncated>
    <difficult>0</difficult>
    <bndbox>
      <xmin>200</xmin>
      <ymin>614</ymin>
      <xmax>338</xmax>
      <ymax>716</ymax>
    </bndbox>
  </object>
  <object>
    <name>trafficLight</name>
    <pose>unspecified</pose>
    <truncated>0</truncated>
    <difficult>0</difficult>
    <bndbox>
      <xmin>238</xmin>
      <ymin>476</ymin>
      <xmax>280</xmax>
      <ymax>558</ymax>
    </bndbox>
  </object>
  <object>
    <name>truck</name>
    <pose>unspecified</pose>
    <truncated>0</truncated>
    <difficult>0</difficult>
    <bndbox>
      <xmin>324</xmin>
      <ymin>630</ymin>
      <xmax>444</xmax>
      <ymax>676</ymax>
    </bndbox>
  </object>
  <object>
    <name>car</name>
    <pose>unspecified</pose>
    <truncated>0</truncated>
    <difficult>0</difficult>
    <bndbox>
      <xmin>324</xmin>
      <ymin>642</ymin>
      <xmax>440</xmax>
      <ymax>706</ymax>
    </bndbox>
  </object>
  <object>
    <name>car</name>
    <pose>unspecified</pose>
    <truncated>0</truncated>
    <difficult>0</difficult>
    <bndbox>
      <xmin>510</xmin>
      <ymin>636</ymin>
      <xmax>652</xmax>
      <ymax>730</ymax>
    </bndbox>
  </object>
  <object>
    <name>car</name>
    <pose>unspecified</pose>
    <truncated>0</truncated>
    <difficult>0</difficult>
    <bndbox>
      <xmin>612</xmin>
      <ymin>638</ymin>
      <xmax>680</xmax>
      <ymax>714</ymax>
    </bndbox>
  </object>
  <object>
    <name>car</name>
    <pose>unspecified</pose>
    <truncated>0</truncated>
    <difficult>0</difficult>
    <bndbox>
      <xmin>918</xmin>
      <ymin>634</ymin>
      <xmax>974</xmax>
      <ymax>714</ymax>
    </bndbox>
  </object>
  <object>
    <name>car</name>
    <pose>unspecified</pose>
    <truncated>0</truncated>
    <difficult>0</difficult>
    <bndbox>
      <xmin>932</xmin>
      <ymin>638</ymin>
      <xmax>1046</xmax>
      <ymax>722</ymax>
    </bndbox>
  </object>
  <object>
    <name>trafficLight</name>
    <pose>unspecified</pose>
    <truncated>0</truncated>
    <difficult>0</difficult>
    <bndbox>
      <xmin>1110</xmin>
      <ymin>426</ymin>
      <xmax>1164</xmax>
      <ymax>524</ymax>
    </bndbox>
  </object>
  <object>
    <name>trafficLight</name>
    <pose>unspecified</pose>
    <truncated>0</truncated>
    <difficult>0</difficult>
    <bndbox>
      <xmin>1548</xmin>
      <ymin>510</ymin>
      <xmax>1594</xmax>
      <ymax>558</ymax>
    </bndbox>
  </object>
</annotation>
